fieldcompare/__about__.py
fieldcompare/__init__.py
fieldcompare/_common.py
fieldcompare/_field.py
fieldcompare/_field_data_comparison.py
fieldcompare/_field_sequence.py
fieldcompare/_format.py
fieldcompare/_matching.py
fieldcompare/_numpy_utils.py
fieldcompare/protocols.py
fieldcompare/_cli/__init__.py
fieldcompare/_cli/_common.py
fieldcompare/_cli/_dir_mode.py
fieldcompare/_cli/_file_comparison.py
fieldcompare/_cli/_file_mode.py
fieldcompare/_cli/_junit.py
fieldcompare/_cli/_logger.py
fieldcompare/_cli/_main.py
fieldcompare/_cli/_test_suite.py
fieldcompare/io/__init__.py
fieldcompare/io/_csv_reader.py
fieldcompare/io/_mesh_io.py
fieldcompare/io/vtk/__init__.py
fieldcompare/io/vtk/_appendix.py
fieldcompare/io/vtk/_compressors.py
fieldcompare/io/vtk/_encoders.py
fieldcompare/io/vtk/_helpers.py
fieldcompare/io/vtk/_pvd_reader.py
fieldcompare/io/vtk/_pvtk_readers.py
fieldcompare/io/vtk/_reader_map.py
fieldcompare/io/vtk/_vti_reader.py
fieldcompare/io/vtk/_vtp_reader.py
fieldcompare/io/vtk/_vtr_reader.py
fieldcompare/io/vtk/_vts_reader.py
fieldcompare/io/vtk/_vtu_reader.py
fieldcompare/io/vtk/_vtu_writer.py
fieldcompare/io/vtk/_xml_reader.py
fieldcompare/mesh/__init__.py
fieldcompare/mesh/_cell_type.py
fieldcompare/mesh/_cell_type_maps.py
fieldcompare/mesh/_mesh.py
fieldcompare/mesh/_mesh_equal.py
fieldcompare/mesh/_mesh_fields.py
fieldcompare/mesh/_mesh_fields_comparator.py
fieldcompare/mesh/_permuted_mesh.py
fieldcompare/mesh/_structured_mesh.py
fieldcompare/mesh/_transformations.py
fieldcompare/mesh/meshio_utils.py
fieldcompare/mesh/protocols.py
fieldcompare/predicates/__init__.py
fieldcompare/predicates/_predicates.py
fieldcompare/tabular/__init__.py
fieldcompare/tabular/_table.py
fieldcompare/tabular/_tabular_fields.py
fieldcompare-0.4.0.dist-info/METADATA
fieldcompare-0.4.0.dist-info/WHEEL
fieldcompare-0.4.0.dist-info/entry_points.txt
fieldcompare-0.4.0.dist-info/top_level.txt
fieldcompare-0.4.0.dist-info/RECORD
