Metadata-Version: 2.4
Name: fieldcompare
Version: 0.4.0
Summary: Read and compare numerical data against reference data using exact, fuzzy or custom comparison operations. Simplify your regression testing pipeline.
Author-email: Dennis Gläser <dennis.glaeser@iws.uni-stuttgart.de>
Maintainer-email: Dennis Gläser <dennis.glaeser@iws.uni-stuttgart.de>
License: GNU GENERAL PUBLIC LICENSE
Project-URL: homepage, https://gitlab.com/dglaeser/fieldcompare
Project-URL: repository, https://gitlab.com/dglaeser/fieldcompare
Keywords: numerical data comparison,regression test,numerical simulation,finite elements,finite volumes
Classifier: Development Status :: 4 - Beta
Classifier: Programming Language :: Python
Requires-Python: >=3.8
Requires-Dist: numpy<3,>=1.26; python_version >= "3.12"
Requires-Dist: numpy<3,>=1.24; python_version < "3.12"
Requires-Dist: colorama<1,>=0.4.3
Provides-Extra: all
Requires-Dist: meshio[all]<6,>=5.3; extra == "all"
Requires-Dist: lz4<5; extra == "all"
